xently/__init__.py
xently/config.py
xently/decorators.py
xently/utils.py
xently/core/__init__.py
xently/core/exceptions.py
xently/core/loading.py
django_xently-1.0.2.dist-info/LICENSE
django_xently-1.0.2.dist-info/METADATA
django_xently-1.0.2.dist-info/WHEEL
django_xently-1.0.2.dist-info/top_level.txt
django_xently-1.0.2.dist-info/RECORD
